onnx_tf/__init__.py
onnx_tf/backend.py
onnx_tf/backend_rep.py
onnx_tf/backend_tf_module.py
onnx_tf/cli.py
onnx_tf/converter.py
onnx_tf/gen_doc.py
onnx_tf/gen_opset.py
onnx_tf/gen_status.py
onnx_tf/opset_version.py
onnx_tf/pb_wrapper.py
onnx_tf/version.py
onnx_tf/common/__init__.py
onnx_tf/common/attr_converter.py
onnx_tf/common/attr_translator.py
onnx_tf/common/data_type.py
onnx_tf/common/exception.py
onnx_tf/common/handler_helper.py
onnx_tf/common/legacy.py
onnx_tf/common/pooling_helper.py
onnx_tf/common/tf_helper.py
onnx_tf/handlers/__init__.py
onnx_tf/handlers/backend_handler.py
onnx_tf/handlers/handler.py
onnx_tf/handlers/backend/__init__.py
onnx_tf/handlers/backend/abs.py
onnx_tf/handlers/backend/acos.py
onnx_tf/handlers/backend/acosh.py
onnx_tf/handlers/backend/add.py
onnx_tf/handlers/backend/and.py
onnx_tf/handlers/backend/arg_max.py
onnx_tf/handlers/backend/arg_min.py
onnx_tf/handlers/backend/asin.py
onnx_tf/handlers/backend/asinh.py
onnx_tf/handlers/backend/atan.py
onnx_tf/handlers/backend/atanh.py
onnx_tf/handlers/backend/average_pool.py
onnx_tf/handlers/backend/batch_normalization.py
onnx_tf/handlers/backend/bitshift.py
onnx_tf/handlers/backend/broadcast_mixin.py
onnx_tf/handlers/backend/cast.py
onnx_tf/handlers/backend/ceil.py
onnx_tf/handlers/backend/celu.py
onnx_tf/handlers/backend/clip.py
onnx_tf/handlers/backend/compress.py
onnx_tf/handlers/backend/concat.py
onnx_tf/handlers/backend/concat_from_sequence.py
onnx_tf/handlers/backend/constant.py
onnx_tf/handlers/backend/constant_fill.py
onnx_tf/handlers/backend/constant_of_shape.py
onnx_tf/handlers/backend/control_flow_mixin.py
onnx_tf/handlers/backend/conv.py
onnx_tf/handlers/backend/conv_integer.py
onnx_tf/handlers/backend/conv_mixin.py
onnx_tf/handlers/backend/conv_transpose.py
onnx_tf/handlers/backend/cos.py
onnx_tf/handlers/backend/cosh.py
onnx_tf/handlers/backend/cumsum.py
onnx_tf/handlers/backend/depth_to_space.py
onnx_tf/handlers/backend/dequantize_linear.py
onnx_tf/handlers/backend/det.py
onnx_tf-1.9.0.dist-info/LICENSE
onnx_tf-1.9.0.dist-info/METADATA
onnx_tf-1.9.0.dist-info/WHEEL
onnx_tf-1.9.0.dist-info/entry_points.txt
onnx_tf-1.9.0.dist-info/top_level.txt
onnx_tf-1.9.0.dist-info/RECORD
